[
  {
    "Column1": "Dataset: Other policy relevant indicators",
    "Column110": null,
    "Column2": null,
    "Column18": null,
    "Column19": null,
    "Column20": null,
    "Column21": null,
    "Column22": null,
    "Column23": null,
    "Column24": null,
    "Column25": null,
    "Column26": null,
    "Column27": null
  },
  {
    "Column1": "Indicator",
    "Column110": null,
    "Column2": null,
    "Column18": null,
    "Column19": null,
    "Column20": null,
    "Column21": null,
    "Column22": null,
    "Column23": null,
    "Column24": null,
    "Column25": null,
    "Column26": null,
    "Column27": null
  },
  {
    "Column1": "Country",
    "Column110": null,
    "Column2": null,
    "Column18": "2015",
    "Column19": "2016",
    "Column20": "2017",
    "Column21": "2018",
    "Column22": "2019",
    "Column23": "2020",
    "Column24": "2021",
    "Column25": "2022",
    "Column26": "2015-2022",
    "Column27": "last year available "
  },
  {
    "Column1": "Albania",
    "Column110": null,
    "Column2": null,
    "Column18": 18.14513,
    "Column19": 17.72032,
    "Column20": 19.35248,
    "Column21": 20.62859,
    "Column22": 18.82147,
    "Column23": 20.11007,
    "Column24": 18.54084,
    "Column25": 20.81203,
    "Column26": 20.81203,
    "Column27": 2022
  },
  {
    "Column1": "Bosnia and Herzegovina",
    "Column110": null,
    "Column2": null,
    "Column18": 16.97994,
    "Column19": 19.70847,
    "Column20": 20.31226,
    "Column21": 21.21636,
    "Column22": 23.52245,
    "Column23": 23.32112,
    "Column24": 23.96216,
    "Column25": 24.51833,
    "Column26": 24.51833,
    "Column27": 2022
  },
  {
    "Column1": "Montenegro",
    "Column110": null,
    "Column2": null,
    "Column18": "..",
    "Column19": "..",
    "Column20": "..",
    "Column21": "..",
    "Column22": 20.45364,
    "Column23": "..",
    "Column24": "..",
    "Column25": "..",
    "Column26": 20.45364,
    "Column27": 2019
  },
  {
    "Column1": "North Macedonia",
    "Column110": null,
    "Column2": null,
    "Column18": 19.95693,
    "Column19": "..",
    "Column20": 21.88985,
    "Column21": 23.57012,
    "Column22": "..",
    "Column23": 20.61319,
    "Column24": 20.6143,
    "Column25": "..",
    "Column26": 20.6143,
    "Column27": 2021
  },
  {
    "Column1": "Serbia",
    "Column110": null,
    "Column2": null,
    "Column18": 25.87672,
    "Column19": 25.90907,
    "Column20": 26.63772,
    "Column21": 28.12624,
    "Column22": 28.35468,
    "Column23": 30.46895,
    "Column24": 30.10267,
    "Column25": 29.82235,
    "Column26": 29.82235,
    "Column27": 2022
  }
]